abstractrepo/__init__.py
abstractrepo/exceptions.py
abstractrepo/order.py
abstractrepo/paging.py
abstractrepo/repo.py
abstractrepo/specification.py
abstractrepo-1.4.3.dist-info/licenses/LICENSE
abstractrepo-1.4.3.dist-info/METADATA
abstractrepo-1.4.3.dist-info/WHEEL
abstractrepo-1.4.3.dist-info/top_level.txt
abstractrepo-1.4.3.dist-info/RECORD
